{
  "generated_at": "2026-07-19T05:25:51.004Z",
  "from": "2026-07-19",
  "to": "2026-09-01",
  "range": 45,
  "events": [
    {
      "date": "2026-07-20",
      "country": "AT",
      "event_name": "Початок Зальцбурзького фестивалю (орієнтовно)",
      "event_type": "festival",
      "relevance_for_bus_company": "medium"
    },
    {
      "date": "2026-07-27",
      "country": "DE",
      "event_name": "Початок літніх канікул (Баден-Вюртемберг)",
      "event_type": "vacation_start",
      "relevance_for_bus_company": "medium"
    },
    {
      "date": "2026-07-30",
      "country": "DE",
      "event_name": "Початок літніх канікул (Баварія)",
      "event_type": "vacation_start",
      "relevance_for_bus_company": "medium"
    },
    {
      "date": "2026-08-05",
      "country": "HU",
      "event_name": "Sziget Festival (Будапешт) (День 1)",
      "event_type": "festival",
      "relevance_for_bus_company": "high"
    },
    {
      "date": "2026-08-06",
      "country": "HU",
      "event_name": "Sziget Festival (Будапешт) (День 2)",
      "event_type": "festival",
      "relevance_for_bus_company": "high"
    },
    {
      "date": "2026-08-07",
      "country": "HU",
      "event_name": "Sziget Festival (Будапешт) (День 3)",
      "event_type": "festival",
      "relevance_for_bus_company": "high"
    },
    {
      "date": "2026-08-08",
      "country": "HU",
      "event_name": "Sziget Festival (Будапешт) (День 4)",
      "event_type": "festival",
      "relevance_for_bus_company": "high"
    },
    {
      "date": "2026-08-09",
      "country": "HU",
      "event_name": "Sziget Festival (Будапешт) (День 5)",
      "event_type": "festival",
      "relevance_for_bus_company": "high"
    },
    {
      "date": "2026-08-10",
      "country": "HU",
      "event_name": "Sziget Festival (Будапешт) (День 6)",
      "event_type": "festival",
      "relevance_for_bus_company": "high"
    },
    {
      "date": "2026-08-11",
      "country": "HU",
      "event_name": "Sziget Festival (Будапешт) (День 7)",
      "event_type": "festival",
      "relevance_for_bus_company": "high"
    },
    {
      "date": "2026-08-12",
      "country": "HU",
      "event_name": "Sziget Festival (Будапешт) (День 8, закінчення)",
      "event_type": "festival",
      "relevance_for_bus_company": "high"
    },
    {
      "date": "2026-08-14",
      "country": "DE",
      "event_name": "Кінець літніх канікул (Саксонія, Саксонія-Ангальт, Тюрингія)",
      "event_type": "vacation_end",
      "relevance_for_bus_company": "high"
    },
    {
      "date": "2026-08-15",
      "country": "DE",
      "event_name": "Mariä Himmelfahrt (Баварія, Саарланд)",
      "event_type": "holiday",
      "relevance_for_bus_company": "medium"
    },
    {
      "date": "2026-08-15",
      "country": "DE",
      "event_name": "Кінець літніх канікул (Гессен, Мекленбург-Передня Померанія, Рейнланд-Пфальц, Саарланд, Шлезвіг-Гольштейн)",
      "event_type": "vacation_end",
      "relevance_for_bus_company": "high"
    },
    {
      "date": "2026-08-15",
      "country": "AT",
      "event_name": "Mariä Himmelfahrt (Assumption Day)",
      "event_type": "holiday",
      "relevance_for_bus_company": "high"
    },
    {
      "date": "2026-08-18",
      "country": "DE",
      "event_name": "Кінець літніх канікул (Північний Рейн-Вестфалія)",
      "event_type": "vacation_end",
      "relevance_for_bus_company": "high"
    },
    {
      "date": "2026-08-20",
      "country": "DE",
      "event_name": "Кінець літніх канікул (Бремен, Гамбург, Нижня Саксонія)",
      "event_type": "vacation_end",
      "relevance_for_bus_company": "high"
    },
    {
      "date": "2026-08-20",
      "country": "HU",
      "event_name": "День святого Стефана",
      "event_type": "holiday",
      "relevance_for_bus_company": "high"
    },
    {
      "date": "2026-08-21",
      "country": "DE",
      "event_name": "Кінець літніх канікул (Берлін)",
      "event_type": "vacation_end",
      "relevance_for_bus_company": "high"
    },
    {
      "date": "2026-08-22",
      "country": "DE",
      "event_name": "Кінець літніх канікул (Бранденбург)",
      "event_type": "vacation_end",
      "relevance_for_bus_company": "high"
    },
    {
      "date": "2026-08-24",
      "country": "UA",
      "event_name": "День Незалежності України",
      "event_type": "holiday",
      "relevance_for_bus_company": "high"
    },
    {
      "date": "2026-08-26",
      "country": "DE",
      "event_name": "Gamescom (Кельн) (День 1)",
      "event_type": "festival",
      "relevance_for_bus_company": "high"
    },
    {
      "date": "2026-08-27",
      "country": "DE",
      "event_name": "Gamescom (Кельн) (День 2)",
      "event_type": "festival",
      "relevance_for_bus_company": "high"
    },
    {
      "date": "2026-08-28",
      "country": "DE",
      "event_name": "Gamescom (Кельн) (День 3)",
      "event_type": "festival",
      "relevance_for_bus_company": "high"
    },
    {
      "date": "2026-08-29",
      "country": "DE",
      "event_name": "Gamescom (Кельн) (День 4)",
      "event_type": "festival",
      "relevance_for_bus_company": "high"
    },
    {
      "date": "2026-08-29",
      "country": "SK",
      "event_name": "Вихідний день Словацького національного повстання",
      "event_type": "holiday",
      "relevance_for_bus_company": "high"
    },
    {
      "date": "2026-08-30",
      "country": "DE",
      "event_name": "Gamescom (Кельн) (День 5, закінчення)",
      "event_type": "festival",
      "relevance_for_bus_company": "high"
    },
    {
      "date": "2026-08-30",
      "country": "AT",
      "event_name": "Кінець літніх канікул (Бургенланд, Нижня Австрія, Відень)",
      "event_type": "vacation_end",
      "relevance_for_bus_company": "high"
    },
    {
      "date": "2026-08-31",
      "country": "UA",
      "event_name": "Кінець літніх канікул (приблизно)",
      "event_type": "vacation_end",
      "relevance_for_bus_company": "high"
    },
    {
      "date": "2026-08-31",
      "country": "AT",
      "event_name": "Кінець Зальцбурзького фестивалю (орієнтовно)",
      "event_type": "festival",
      "relevance_for_bus_company": "medium"
    },
    {
      "date": "2026-08-31",
      "country": "SK",
      "event_name": "Кінець літніх канікул",
      "event_type": "vacation_end",
      "relevance_for_bus_company": "high"
    },
    {
      "date": "2026-08-31",
      "country": "HU",
      "event_name": "Кінець літніх канікул",
      "event_type": "vacation_end",
      "relevance_for_bus_company": "high"
    }
  ]
}